<annotation>
	<folder>NewRasters</folder>
	<filename>139.jpg</filename>
	<path>C:\Users\khoal\Desktop\Sattelite\NewRasters\139.jpg</path>
	<source>
		<database>Unknown</database>
	</source>
	<size>
		<width>650</width>
		<height>650</height>
		<depth>3</depth>
	</size>
	<segmented>0</segmented>
	<object>
		<name>parking lot</name>
		<pose>Unspecified</pose>
		<truncated>0</truncated>
		<difficult>0</difficult>
		<bndbox>
			<xmin>279</xmin>
			<ymin>138</ymin>
			<xmax>331</xmax>
			<ymax>187</ymax>
		</bndbox>
	</object>
	<object>
		<name>parking lot</name>
		<pose>Unspecified</pose>
		<truncated>0</truncated>
		<difficult>0</difficult>
		<bndbox>
			<xmin>240</xmin>
			<ymin>82</ymin>
			<xmax>295</xmax>
			<ymax>121</ymax>
		</bndbox>
	</object>
	<object>
		<name>parking lot</name>
		<pose>Unspecified</pose>
		<truncated>0</truncated>
		<difficult>0</difficult>
		<bndbox>
			<xmin>224</xmin>
			<ymin>128</ymin>
			<xmax>268</xmax>
			<ymax>169</ymax>
		</bndbox>
	</object>
</annotation>
