<annotation>
	<folder>Thomas</folder>
	<filename>665.jpg</filename>
	<path>C:\Users\khoal\Desktop\Sattelite\Thomas\665.jpg</path>
	<source>
		<database>Unknown</database>
	</source>
	<size>
		<width>650</width>
		<height>650</height>
		<depth>3</depth>
	</size>
	<segmented>0</segmented>
	<object>
		<name>parking lot</name>
		<pose>Unspecified</pose>
		<truncated>0</truncated>
		<difficult>0</difficult>
		<bndbox>
			<xmin>2</xmin>
			<ymin>444</ymin>
			<xmax>139</xmax>
			<ymax>642</ymax>
		</bndbox>
	</object>
	<object>
		<name>parking lot</name>
		<pose>Unspecified</pose>
		<truncated>0</truncated>
		<difficult>0</difficult>
		<bndbox>
			<xmin>142</xmin>
			<ymin>246</ymin>
			<xmax>345</xmax>
			<ymax>410</ymax>
		</bndbox>
	</object>
	<object>
		<name>parking lot</name>
		<pose>Unspecified</pose>
		<truncated>0</truncated>
		<difficult>0</difficult>
		<bndbox>
			<xmin>351</xmin>
			<ymin>134</ymin>
			<xmax>541</xmax>
			<ymax>257</ymax>
		</bndbox>
	</object>
	<object>
		<name>parking lot</name>
		<pose>Unspecified</pose>
		<truncated>1</truncated>
		<difficult>0</difficult>
		<bndbox>
			<xmin>508</xmin>
			<ymin>295</ymin>
			<xmax>650</xmax>
			<ymax>423</ymax>
		</bndbox>
	</object>
	<object>
		<name>parking lot</name>
		<pose>Unspecified</pose>
		<truncated>0</truncated>
		<difficult>0</difficult>
		<bndbox>
			<xmin>460</xmin>
			<ymin>501</ymin>
			<xmax>631</xmax>
			<ymax>629</ymax>
		</bndbox>
	</object>
</annotation>
